kaze_python_rpc-1.0.0.0.dist-info/METADATA
kaze_python_rpc-1.0.0.0.dist-info/RECORD
kaze_python_rpc-1.0.0.0.dist-info/WHEEL
kaze_python_rpc-1.0.0.0.dist-info/top_level.txt
kazerpc/Client.py
kazerpc/Settings.py
kazerpc/__init__.py
