Metadata-Version: 2.1
Name: kaze-python-rpc
Version: 1.0.0.0
Summary: A Python RPC Client for the kaze Blockchain
Home-page: https://github.com/KAZEBLOCKCHAIN/kaze-python-rpc
Author: Moe Sayadi
Author-email: moe@kazesolutions.ch
License: MIT license
Keywords: kaze,python,rpc,client
Platform: UNKNOWN
Classifier: Development Status :: 2 - Pre-Alpha
Classifier: Intended Audience :: Developers
Classifier: License :: OSI Approved :: MIT License
Classifier: Natural Language :: English
Classifier: Programming Language :: Python :: 3
Classifier: Programming Language :: Python :: 3.3
Classifier: Programming Language :: Python :: 3.4
Classifier: Programming Language :: Python :: 3.5
Classifier: Programming Language :: Python :: 3.6
Requires-Dist: requests
